script/__init__.py
script/bam2bigg.py
script/bigg2b.py
script/bigg2len.py
script/bigg2seq.py
script/biggmutant.py
script/gff2bigg.py
script/trackrun.py
test/__init__.py
test/batch_test.py
test/cluster_test.py
test/clustercj_test.py
test/clusterj_test.py
test/convert_test.py
test/flow_test.py
test/gff_test.py
test/post_test.py
test/pre_test.py
test/track_test.py
test/tracklist_test.py
test/utils_test.py
trackcluster/__init__.py
trackcluster/batch.py
trackcluster/cluster.py
trackcluster/clustercj.py
trackcluster/clusterj.py
trackcluster/convert.py
trackcluster/flow.py
trackcluster/gff.py
trackcluster/post.py
trackcluster/pre.py
trackcluster/track.py
trackcluster/tracklist.py
trackcluster/utils.py
trackcluster-0.1.7.data/scripts/bam2bigg.py
trackcluster-0.1.7.data/scripts/bigg2b.py
trackcluster-0.1.7.data/scripts/bigg2len.py
trackcluster-0.1.7.data/scripts/biggmutant.py
trackcluster-0.1.7.data/scripts/gff2bigg.py
trackcluster-0.1.7.data/scripts/trackrun.py
trackcluster-0.1.7.dist-info/METADATA
trackcluster-0.1.7.dist-info/WHEEL
trackcluster-0.1.7.dist-info/top_level.txt
trackcluster-0.1.7.dist-info/RECORD
