Metadata-Version: 2.1
Name: trackcluster
Version: 0.1.7
Summary: RNA-seq analysis for Long read RNA sequencing
Home-page: https://github.com/runsheng/trackcluster
Author: runsheng
Author-email: runsheng.lee@gmail.com
License: GPL-2
Platform: UNKNOWN
Requires-Dist: biopython (>=1.78)
Requires-Dist: numpy (>=1.19.4)
Requires-Dist: pandas (>=1.1.5)
Requires-Dist: pysam (>=0.16.0.1)
Requires-Dist: tqdm (>=4.64.0)
